sphinx_table_gen/__init__.py
sphinx_table_gen/main.py
sphinx_table_gen-0.0.2.dist-info/LICENSE
sphinx_table_gen-0.0.2.dist-info/METADATA
sphinx_table_gen-0.0.2.dist-info/WHEEL
sphinx_table_gen-0.0.2.dist-info/top_level.txt
sphinx_table_gen-0.0.2.dist-info/RECORD
